layup/__init__.py
layup-0.0.1.dist-info/METADATA
layup-0.0.1.dist-info/WHEEL
layup-0.0.1.dist-info/top_level.txt
layup-0.0.1.dist-info/RECORD
