Metadata-Version: 2.2
Name: layup
Version: 0.0.1
Summary: An orbit fitting package
Author-email: Matthew J Holman <mholman@cfa.harvard.edu>
Requires-Python: >=3.8
